Metadata-Version: 1.1
Name: windows-rbs-parser
Version: 0.0.1
Summary: Python library/tool which is able to parse .rbs files used by the windows diagnostics framework
Home-page: https://github.com/bluec0re/windows-rbs-parser
Author: BlueC0re
Author-email: info@bluec0re.eu
License: MIT
Platform: UNKNOWN
Classifier: Development Status :: 2 - Pre-Alpha
Classifier: Intended Audience :: Developers
Classifier: Intended Audience :: System Administrators
Classifier: License :: OSI Approved :: MIT License
Classifier: Programming Language :: Python :: 3
Classifier: Topic :: Utilities
